<?xml version="1.0" encoding="UTF-8"?>
<buildConfigurations xmlns="http://difi.no/xsd/vefa/validator/1.0">

    <package>Peppol Waybill 1.1</package>

    <configuration>
        <identifier>peppolbis-T125-base-1.0</identifier>
        <title>Waybill (T125)</title>
        <inherit>ubl-waybill-2.3</inherit>
        <file source="../../../_source/poacc-logistics/target/schematron/PEPPOLBIS-T125.sch" path="sch/PEPPOLBIS-T125.sch"/>
    </configuration>

    <configuration>
        <identifier>peppolbis-125</identifier>
        <title>Waybill</title>
        <profileId>urn:fdc:peppol.eu:logistics:bis:waybill_only:1</profileId>
        <customizationId>urn:fdc:peppol.eu:logistics:trns:waybill:1</customizationId>
        <inherit>peppolbis-T125-base-1.0</inherit>
    </configuration>

</buildConfigurations>