<?xml version="1.0" encoding="UTF-8"?>
<buildConfigurations xmlns="http://difi.no/xsd/vefa/validator/1.0">

    <package>EHF Forward Billing 3.0.2</package>

    <testfolder>example</testfolder>

    <configuration>
        <identifier>ehf-forward-billing-base-3.0</identifier>
        <title>EHF Forward Billing 3.0</title>
        <file source="../../../target/schematron-peppol/FORWARD-BILLING-CEN-EN16931-UBL.sch" path="sch/EHF-FORWARD-BILLING-3.0-CEN.sch" />
        <file source="../../../target/schematron-peppol/FORWARD-BILLING-PEPPOL-EN16931-UBL.sch" path="sch/EHF-FORWARD-BILLING-3.0-PEPPOL.sch" />
    </configuration>

    <configuration>
        <identifier>ehf-forward-billing-08-3.0</identifier>
        <title>EHF Forward Billing 3.0 (Profile 08)</title>
        <profileId>urn:fdc:anskaffelser.no:2019:ehf:postaward:g3:08:1.0</profileId>
        <customizationId>urn:cen.eu:en16931:2017#compliant#urn:fdc:peppol.eu:2017:poacc:billing:3.0#conformant#urn:fdc:anskaffelser.no:2019:ehf:forward-billing:3.0</customizationId>
        <inherit>ubl-invoice-2.1</inherit>
        <inherit>ehf-forward-billing-base-3.0</inherit>
    </configuration>

</buildConfigurations>
